domb/__init__.py
domb/fret/__init__.py
domb/fret/b_fret/__init__.py
domb/fret/b_fret/main.py
domb/fret/b_fret/param_dist_funcs.py
domb/fret/b_fret/state_dist_funcs.py
domb/fret/b_fret/utils.py
domb/fret/b_fret/example/gauss_noise/sinusoids/define_analysis_params.py
domb/fret/b_fret/example/gauss_noise/sinusoids/define_model_functions.py
domb/fret/b_fret/example/gauss_noise/steps/define_analysis_params.py
domb/fret/b_fret/example/gauss_noise/steps/define_model_functions.py
domb/fret/b_fret/example/non_gauss_noise/sinusoids/define_analysis_params.py
domb/fret/b_fret/example/non_gauss_noise/sinusoids/define_model_functions.py
domb/fret/b_fret/example/non_gauss_noise/steps/define_analysis_params.py
domb/fret/b_fret/example/non_gauss_noise/steps/define_model_functions.py
domb/fret/b_fret/scripts/sample_run_script.py
domb/fret/e_fret/__init__.py
domb/fret/e_fret/coef_calc.py
domb/fret/e_fret/e_app.py
domb/red_green/__init__.py
domb/red_green/wt_vs_mut.py
domb/red_green/wt_vs_mut_multistim.py
domb/reg_type/__init__.py
domb/reg_type/wf_x2_m2.py
domb/utils/__init__.py
domb/utils/masking.py
domb/utils/oiffile.py
domb/utils/plot.py
domb-2023.11.3.dist-info/LICENSE
domb-2023.11.3.dist-info/METADATA
domb-2023.11.3.dist-info/WHEEL
domb-2023.11.3.dist-info/top_level.txt
domb-2023.11.3.dist-info/RECORD
