Metadata-Version: 2.1
Name: domb
Version: 2023.11.3
Summary: DoMB Tools: Python Toolkit of Department of Molecular Biophysics
Author-email: Borys Olifirov <omnia.fatum@gmail.com>
License: Copyright (c) 2023 Borys Olifirov <omnia.fatum@gmail.com>
Project-URL: Documentation, https://domb.bio/
Project-URL: Repository, https://github.com/wisstock/DoMB_tools
Classifier: Development Status :: 3 - Alpha
Classifier: License :: OSI Approved :: MIT License
Classifier: Programming Language :: Python :: 3.9
Classifier: Operating System :: OS Independent
Classifier: Framework :: IPython
Classifier: Framework :: Jupyter
Classifier: Topic :: Scientific/Engineering :: Bio-Informatics
Classifier: Topic :: Scientific/Engineering :: Image Processing
Classifier: Topic :: Scientific/Engineering :: Image Recognition
Classifier: Topic :: Utilities
Requires-Python: >=3.8
License-File: LICENSE
Requires-Dist: matplotlib
Requires-Dist: numpy
Requires-Dist: pandas
Requires-Dist: scikit-image
Requires-Dist: scikit-learn
Requires-Dist: scikit-posthocs
Requires-Dist: scipy
